xml_formatter.py
xml_formatter_plus-0.1.1.dist-info/METADATA
xml_formatter_plus-0.1.1.dist-info/WHEEL
xml_formatter_plus-0.1.1.dist-info/entry_points.txt
xml_formatter_plus-0.1.1.dist-info/top_level.txt
xml_formatter_plus-0.1.1.dist-info/RECORD
