Metadata-Version: 2.2
Name: xml-formatter-plus
Version: 0.1.1
Summary: A Python package that formats and beautifies XML strings with HTML entity handling
Home-page: https://github.com/yash11K/html-escape
Author: Yash Kabra
Author-email: yash11kabra@gmail.com
Classifier: Programming Language :: Python :: 3
Classifier: Programming Language :: Python :: 3.6
Classifier: Programming Language :: Python :: 3.7
Classifier: Programming Language :: Python :: 3.8
Classifier: Programming Language :: Python :: 3.9
Classifier: License :: OSI Approved :: MIT License
Classifier: Operating System :: OS Independent
Requires-Python: >=3.6
Dynamic: author
Dynamic: author-email
Dynamic: classifier
Dynamic: home-page
Dynamic: requires-python
Dynamic: summary
